setup.py
fluff/__init__.py
fluff/logging2.py
fluff.egg-info/PKG-INFO
fluff.egg-info/SOURCES.txt
fluff.egg-info/dependency_links.txt
fluff.egg-info/not-zip-safe
fluff.egg-info/top_level.txt