Metadata-Version: 1.0
Name: fluff
Version: 0.1
Summary: Extra tools for PyLint
Home-page: https://github.com/dstufft/fluff/
Author: UNKNOWN
Author-email: UNKNOWN
License: UNKNOWN
Platform: UNKNOWN
